simple_python_app/__init__.py
simple_python_app/_version.py
simple_python_app/generic_application.py
simple_python_app/py.typed
simple_python_app/subcommand_application.py
simple_python_app/resources/default_logging_config.yaml
simple_python_app-0.4.1.dist-info/LICENSE
simple_python_app-0.4.1.dist-info/METADATA
simple_python_app-0.4.1.dist-info/WHEEL
simple_python_app-0.4.1.dist-info/top_level.txt
simple_python_app-0.4.1.dist-info/RECORD
