Metadata-Version: 2.1
Name: simple_python_app
Version: 0.4.1
Summary: Simple framework that provides preconfigured components that most applications need.
Home-page: https://github.com/twyleg/simple_python_app
Author: Torsten Wylegala
Author-email: mail@twyleg.de
License: GPL 3.0
Keywords: framework boilerplate logging argparse config
License-File: LICENSE
Requires-Dist: pyyaml ~=6.0.2
Requires-Dist: types-PyYAML ~=6.0.12.20240808
Requires-Dist: jsonschema ~=4.20.0
Requires-Dist: types-jsonschema ~=4.23.0.20240813
Requires-Dist: prompt-toolkit ~=3.0.48
Requires-Dist: types-colorama ~=0.4.15.20240311
